BGdist2020/Binomialdistribution.py
BGdist2020/Gaussiandistribution.py
BGdist2020/Generaldistribution.py
BGdist2020/__init__.py
BGdist2020-0.4.dist-info/DESCRIPTION.rst
BGdist2020-0.4.dist-info/METADATA
BGdist2020-0.4.dist-info/RECORD
BGdist2020-0.4.dist-info/WHEEL
BGdist2020-0.4.dist-info/metadata.json
BGdist2020-0.4.dist-info/top_level.txt
