Metadata-Version: 2.0
Name: BGdist2020
Version: 0.4
Summary: Gaussian distributions
Home-page: UNKNOWN
Author: Noel Conlisk
Author-email: UNKNOWN
License: UNKNOWN
Platform: UNKNOWN
Classifier: Programming Language :: Python :: 3
Classifier: License :: OSI Approved :: MIT License
Classifier: Operating System :: OS Independent
Requires-Python: >=3.0
